MANIFEST.in
readme.md
setup.py
mangopi/__init__.py
mangopi/metasite.py
mangopi.egg-info/PKG-INFO
mangopi.egg-info/SOURCES.txt
mangopi.egg-info/dependency_links.txt
mangopi.egg-info/requires.txt
mangopi.egg-info/top_level.txt
mangopi/helper/__init__.py
mangopi/helper/decorators.py
mangopi/helper/image.py
mangopi/helper/util.py
mangopi/helper/traits/__init__.py
mangopi/helper/traits/hasurl.py
mangopi/site/__init__.py
mangopi/site/aftv.py
mangopi/site/mangafox.py
mangopi/site/mangahere.py
mangopi/site/mangapanda.py
mangopi/site/mangareader.py
mangopi/site/mangasite.py
mangopi/site/noez.py