Metadata-Version: 1.0
Name: mangopi
Version: 0.2.1.1
Summary: A manga API with a pluggable site architecture.
Home-page: https://github.com/jiaweihli/mangopi/
Author: Jiawei Li
Author-email: jiawei.h.li@gmail.com
License: MIT
Keywords: manga api
Platform: UNKNOWN
